{
  "language": "es_ES",
  "id": "A1-155",
  "name": "Hitmonchan",
  "localId": "155",
  "category": "Pokémon",
  "set": {
    "id": "A1",
    "name": "Genes Formidables"
  },
  "rarity": "Une Diamant",
  "cardImage": "/assets/cardImage/es_ES/A1/A1-155_card.png",
  "artworkImage": "/assets/artworkImage/A1/A1-155_artwork.png",
  "illustrator": "Ken Sugimori",
  "hp": 80,
  "types": [
    "Lucha"
  ],
  "stage": "Basico",
  "evolveFrom": null,
  "isEx": false,
  "isUltraBeast": false,
  "abilities": [],
  "attacks": [
    {
      "cost": [
        "Lucha"
      ],
      "name": "Puya",
      "damage": {
        "value": 30,
        "modifier": null
      },
      "effect": ""
    }
  ],
  "weaknesses": [
    {
      "type": "Psíquico",
      "value": "+20"
    }
  ],
  "rules": [],
  "retreat": [
    "Colorless"
  ],
  "description": "Sus puñetazos cortan el aire. Son tan veloces que\nel mínimo roce podría causar una quemadura."
}