{
  "language": "de_DE",
  "id": "P-A-069",
  "name": "Alola-Kokowei",
  "localId": "069",
  "category": "Pokémon",
  "set": {
    "id": "P-A",
    "name": "PROMO-A"
  },
  "rarity": "Trois Diamant",
  "cardImage": "/assets/cardImage/de_DE/P-A/P-A-069_card.png",
  "artworkImage": "/assets/artworkImage/P-A/P-A-069_artwork.png",
  "illustrator": "Satoshi Shirai",
  "hp": 150,
  "types": [
    "Pflanze"
  ],
  "stage": "Rang 1",
  "evolveFrom": null,
  "isEx": false,
  "isUltraBeast": false,
  "abilities": [],
  "attacks": [
    {
      "cost": [
        "Pflanze",
        "Farblos",
        "Farblos"
      ],
      "name": "Tropischer Hammer",
      "damage": {
        "value": 150,
        "modifier": null
      },
      "effect": "Wirf 1 Münze. Bei Zahl hat diese Attacke keine Auswirkungen."
    }
  ],
  "weaknesses": [
    {
      "type": "Feuer",
      "value": "+20"
    }
  ],
  "rules": [],
  "retreat": [
    "Colorless",
    "Colorless",
    "Colorless",
    "Colorless"
  ],
  "description": "Durch starke Sonneneinstrahlung wurden seine\neigentlichen Kräfte und seine wahre Gestalt freigesetzt."
}