{
  "language": "pt_BR",
  "id": "A2-054",
  "name": "Voltorb",
  "localId": "054",
  "category": "Pokemon",
  "set": {
    "id": "A2",
    "name": "Embate do Tempo e Espaço"
  },
  "rarity": "One Diamond",
  "cardImage": "/assets/cardImage/pt_BR/A2/A2-054_card.png",
  "artworkImage": "/assets/artworkImage/A2/A2-054_artwork.png",
  "illustrator": "Midori Harada",
  "hp": 60,
  "types": [
    "Lightning"
  ],
  "stage": "Basic",
  "evolveFrom": null,
  "isEx": false,
  "isUltraBeast": false,
  "abilities": [],
  "attacks": [
    {
      "cost": [
        "Lightning"
      ],
      "name": "Grande Explosão",
      "damage": {
        "value": 30,
        "modifier": null
      },
      "effect": "Este Pokémon também causa 10 pontos de dano a si mesmo."
    }
  ],
  "weaknesses": [
    {
      "type": "Fighting",
      "value": "+20"
    }
  ],
  "rules": [],
  "retreat": [
    "Colorless"
  ],
  "description": "Ele rola para se mover. Quando o solo está\ndesnivelado, um solavanco repentino após\num baque pode fazê-lo explodir."
}