{
  "language": "it_IT",
  "id": "A2b-015",
  "name": "Tentacruel",
  "localId": "015",
  "category": "Pokémon",
  "set": {
    "id": "A2b",
    "name": "Tripudio Splendente"
  },
  "rarity": "deux Diamant",
  "cardImage": "/assets/cardImage/it_IT/A2b/A2b-015_card.png",
  "artworkImage": "/assets/artworkImage/A2b/A2b-015_artwork.png",
  "illustrator": "match",
  "hp": 100,
  "types": [
    "Acqua"
  ],
  "stage": "Livello 1",
  "evolveFrom": null,
  "isEx": false,
  "isUltraBeast": false,
  "abilities": [],
  "attacks": [
    {
      "cost": [
        "Acqua"
      ],
      "name": "Schizzi d'Onda",
      "damage": {
        "value": 40,
        "modifier": null
      },
      "effect": ""
    }
  ],
  "weaknesses": [
    {
      "type": "Lampo",
      "value": "+20"
    }
  ],
  "rules": [],
  "retreat": [
    "Colorless"
  ],
  "description": "Meglio fare attenzione quando le sfere rosse\nche ha sulla testa brillano intensamente, perché\nvuol dire che sta per emettere ultrasuoni."
}