{
  "language": "it_IT",
  "id": "A2a-051",
  "name": "Croagunk",
  "localId": "051",
  "category": "Pokémon",
  "set": {
    "id": "A2a",
    "name": "Luce Trionfale"
  },
  "rarity": "Une Diamant",
  "cardImage": "/assets/cardImage/it_IT/A2a/A2a-051_card.png",
  "artworkImage": "/assets/artworkImage/A2a/A2a-051_artwork.png",
  "illustrator": "SATOSHI NAKAI",
  "hp": 60,
  "types": [
    "Oscurità"
  ],
  "stage": "Base",
  "evolveFrom": null,
  "isEx": false,
  "isUltraBeast": false,
  "abilities": [],
  "attacks": [
    {
      "cost": [
        "Oscurità"
      ],
      "name": "Battuta",
      "damage": {
        "value": 20,
        "modifier": null
      },
      "effect": ""
    }
  ],
  "weaknesses": [
    {
      "type": "Lotta",
      "value": "+20"
    }
  ],
  "rules": [],
  "retreat": [
    "Colorless"
  ],
  "description": "Gonfia le sue sacche di veleno emettendo un verso\nsinistro che fa impietrire l'avversario, poi lo avvelena."
}