{
  "language": "it_IT",
  "id": "A2a-063",
  "name": "Snorlax",
  "localId": "063",
  "category": "Pokémon",
  "set": {
    "id": "A2a",
    "name": "Luce Trionfale"
  },
  "rarity": "deux Diamant",
  "cardImage": "/assets/cardImage/it_IT/A2a/A2a-063_card.png",
  "artworkImage": "/assets/artworkImage/A2a/A2a-063_artwork.png",
  "illustrator": "burari",
  "hp": 140,
  "types": [
    "Incolore"
  ],
  "stage": "Base",
  "evolveFrom": null,
  "isEx": false,
  "isUltraBeast": false,
  "abilities": [],
  "attacks": [
    {
      "cost": [
        "Incolore",
        "Incolore",
        "Incolore",
        "Incolore"
      ],
      "name": "Collassare",
      "damage": {
        "value": 100,
        "modifier": null
      },
      "effect": "Questo Pokémon viene addormentato."
    }
  ],
  "weaknesses": [
    {
      "type": "Lotta",
      "value": "+20"
    }
  ],
  "rules": [],
  "retreat": [
    "Colorless",
    "Colorless",
    "Colorless",
    "Colorless"
  ],
  "description": "Dopo aver trangugiato i suoi immancabili 400 kg\ndi cibo quotidiani, cade in un sonno profondo."
}