{
  "language": "it_IT",
  "id": "A3-218",
  "name": "Staryu",
  "localId": "218",
  "category": "Pokémon",
  "set": {
    "id": "A3",
    "name": "Guardiani Astrali"
  },
  "rarity": "Un Chromatique",
  "cardImage": "/assets/cardImage/it_IT/A3/A3-218_card.png",
  "artworkImage": "/assets/artworkImage/A3/A3-218_artwork.png",
  "illustrator": "MAHOU",
  "hp": 50,
  "types": [
    "Acqua"
  ],
  "stage": "Base",
  "evolveFrom": null,
  "isEx": false,
  "isUltraBeast": false,
  "abilities": [],
  "attacks": [
    {
      "cost": [
        "Acqua"
      ],
      "name": "Schiaffo",
      "damage": {
        "value": 20,
        "modifier": null
      },
      "effect": ""
    }
  ],
  "weaknesses": [
    {
      "type": "Lampo",
      "value": "+20"
    }
  ],
  "rules": [],
  "retreat": [
    "Colorless"
  ],
  "description": "Alla fine dell'estate, sui litorali è\npossibile osservare gruppi di Staryu\nche emettono luce a un ritmo regolare."
}