{
  "language": "fr_FR",
  "id": "A2a-080",
  "name": "Magnéti",
  "localId": "080",
  "category": "Pokémon",
  "set": {
    "id": "A2a",
    "name": "Lumière Triomphale"
  },
  "rarity": "Une Étoile",
  "cardImage": "/assets/cardImage/fr_FR/A2a/A2a-080_card.png",
  "artworkImage": "/assets/artworkImage/A2a/A2a-080_artwork.png",
  "illustrator": "Yukihiro Tada",
  "hp": 60,
  "types": [
    "Métal"
  ],
  "stage": "De base",
  "evolveFrom": null,
  "isEx": false,
  "isUltraBeast": false,
  "abilities": [],
  "attacks": [
    {
      "cost": [
        "Métal"
      ],
      "name": "Charge",
      "damage": {
        "value": 20,
        "modifier": null
      },
      "effect": ""
    }
  ],
  "weaknesses": [
    {
      "type": "Feu",
      "value": "+20"
    }
  ],
  "rules": [],
  "retreat": [
    "Colorless"
  ],
  "description": "Les ondes électromagnétiques émises par ses extrémités\nlui permettent de défier les lois de la gravité et de flotter."
}