{
  "language": "it_IT",
  "id": "P-A-060",
  "name": "Exeggcute",
  "localId": "060",
  "category": "Pokémon",
  "set": {
    "id": "P-A",
    "name": "Promo-A"
  },
  "rarity": "Une Diamant",
  "cardImage": "/assets/cardImage/it_IT/P-A/P-A-060_card.png",
  "artworkImage": "/assets/artworkImage/P-A/P-A-060_artwork.png",
  "illustrator": "0313",
  "hp": 50,
  "types": [
    "Erba"
  ],
  "stage": "Base",
  "evolveFrom": null,
  "isEx": false,
  "isUltraBeast": false,
  "abilities": [],
  "attacks": [
    {
      "cost": [
        "Incolore"
      ],
      "name": "Crescita Inaspettata",
      "damage": {
        "value": null,
        "modifier": null
      },
      "effect": "Prendi un'Energia {G} dalla tua Zona Energia e assegnala a questo Pokémon."
    }
  ],
  "weaknesses": [
    {
      "type": "Fuoco",
      "value": "+20"
    }
  ],
  "rules": [],
  "retreat": [
    "Colorless"
  ],
  "description": "Somiglia a un mucchio di uova, ma è\nun Pokémon a tutti gli effetti. Pare che\ncomunichi con i suoi simili telepaticamente."
}