{
  "language": "pt_BR",
  "id": "A3-026",
  "name": "Arcanine",
  "localId": "026",
  "category": "Pokemon",
  "set": {
    "id": "A3",
    "name": "Guardiões Celestiais"
  },
  "rarity": "Two Diamond",
  "cardImage": "/assets/cardImage/pt_BR/A3/A3-026_card.png",
  "artworkImage": "/assets/artworkImage/A3/A3-026_artwork.png",
  "illustrator": "match",
  "hp": 130,
  "types": [
    "Fire"
  ],
  "stage": "Stage1",
  "evolveFrom": null,
  "isEx": false,
  "isUltraBeast": false,
  "abilities": [],
  "attacks": [
    {
      "cost": [
        "Fire",
        "Fire",
        "Colorless"
      ],
      "name": "Crina de Fogo",
      "damage": {
        "value": 80,
        "modifier": null
      },
      "effect": ""
    }
  ],
  "weaknesses": [
    {
      "type": "Water",
      "value": "+20"
    }
  ],
  "rules": [],
  "retreat": [
    "Colorless",
    "Colorless",
    "Colorless"
  ],
  "description": "Um antigo pergaminho mostra que pessoas eram\ncativadas por seu movimento enquanto este\nPokémon corria pelas pradarias."
}