{
  "language": "fr_FR",
  "id": "A3-035",
  "name": "Tritox",
  "localId": "035",
  "category": "Pokémon",
  "set": {
    "id": "A3",
    "name": "Gardiens Astraux"
  },
  "rarity": "Une Diamant",
  "cardImage": "/assets/cardImage/fr_FR/A3/A3-035_card.png",
  "artworkImage": "/assets/artworkImage/A3/A3-035_artwork.png",
  "illustrator": "Yukiko Baba",
  "hp": 50,
  "types": [
    "Feu"
  ],
  "stage": "De base",
  "evolveFrom": null,
  "isEx": false,
  "isUltraBeast": false,
  "abilities": [],
  "attacks": [
    {
      "cost": [
        "Incolore"
      ],
      "name": "Ronge",
      "damage": {
        "value": 20,
        "modifier": null
      },
      "effect": ""
    }
  ],
  "weaknesses": [
    {
      "type": "Eau",
      "value": "+20"
    }
  ],
  "rules": [],
  "retreat": [
    "Colorless"
  ],
  "description": "Il provoque ses proies afin de les attirer dans\nd'étroites zones rocheuses, puis il les étourdit\navec son gaz toxique avant de les achever."
}