{
  "language": "fr_FR",
  "id": "A3-030",
  "name": "Flamiaou",
  "localId": "030",
  "category": "Pokémon",
  "set": {
    "id": "A3",
    "name": "Gardiens Astraux"
  },
  "rarity": "Une Diamant",
  "cardImage": "/assets/cardImage/fr_FR/A3/A3-030_card.png",
  "artworkImage": "/assets/artworkImage/A3/A3-030_artwork.png",
  "illustrator": "Akira Komayama",
  "hp": 60,
  "types": [
    "Feu"
  ],
  "stage": "De base",
  "evolveFrom": null,
  "isEx": false,
  "isUltraBeast": false,
  "abilities": [],
  "attacks": [
    {
      "cost": [
        "Feu"
      ],
      "name": "Charge Énergétique",
      "damage": {
        "value": 30,
        "modifier": null
      },
      "effect": "Ce Pokémon s'inflige aussi 10 dégâts."
    }
  ],
  "weaknesses": [
    {
      "type": "Eau",
      "value": "+20"
    }
  ],
  "rules": [],
  "retreat": [
    "Colorless"
  ],
  "description": "Il se renferme sur lui-même si on lui accorde\ntrop d'attention. Mieux vaut éviter de beaucoup\nle caresser, même s'il devient affectueux."
}