{
  "language": "es_ES",
  "id": "A2b-017",
  "name": "Floatzel",
  "localId": "017",
  "category": "Pokémon",
  "set": {
    "id": "A2b",
    "name": "Festival Brillante"
  },
  "rarity": "deux Diamant",
  "cardImage": "/assets/cardImage/es_ES/A2b/A2b-017_card.png",
  "artworkImage": "/assets/artworkImage/A2b/A2b-017_artwork.png",
  "illustrator": "Kouki Saitou",
  "hp": 90,
  "types": [
    "Agua"
  ],
  "stage": "Fase 1",
  "evolveFrom": null,
  "isEx": false,
  "isUltraBeast": false,
  "abilities": [],
  "attacks": [
    {
      "cost": [
        "Agua"
      ],
      "name": "Flecha de Agua",
      "damage": {
        "value": null,
        "modifier": null
      },
      "effect": "Este ataque hace 30 puntos de daño a 1 de los Pokémon de tu rival."
    }
  ],
  "weaknesses": [
    {
      "type": "Rayo",
      "value": "+20"
    }
  ],
  "rules": [],
  "retreat": [
    "Colorless"
  ],
  "description": "Con la vejiga natatoria inflada, puede llevar a personas\nsobre su espalda. Antes de bucear, la desinfla."
}